mypackage/__init__.py
mypackage/packet search/__init__.py
mypackage/packet search/search.py
mypackage/packet webatack/__init__.py
mypackage/packet webatack/webattack.py
webhacking-2.2.dist-info/licenses/LICENCE
webhacking-2.2.dist-info/METADATA
webhacking-2.2.dist-info/WHEEL
webhacking-2.2.dist-info/top_level.txt
webhacking-2.2.dist-info/RECORD
