Metadata-Version: 2.4
Name: webhacking
Version: 2.2
Summary: взломай сайт
Home-page: https://github.com/vova1f/webhacking
Author: vova2f
Author-email: vovk4756@gmail.com
Classifier: Programming Language :: Python :: 3
Classifier: License :: OSI Approved :: MIT License
Classifier: Operating System :: OS Independent
Requires-Python: >=3.12
License-File: LICENCE
Requires-Dist: somepackage>=1.1.0
Requires-Dist: ipaddress==1.0.23
Requires-Dist: socket
Requires-Dist: trio-websocket==0.12.2
Requires-Dist: colorama==0.4.2
Requires-Dist: requests==2.32.5
Requires-Dist: threading
Requires-Dist: websocket-client==1.8.0
Dynamic: author
Dynamic: author-email
Dynamic: classifier
Dynamic: description
Dynamic: description-content-type
Dynamic: home-page
Dynamic: license-file
Dynamic: requires-dist
Dynamic: requires-python
Dynamic: summary
